{
    "prepare_queue": {
        "installed": [],
        "uninstalled": []
    },
    "config_munge": {
        "files": {
            "framework": {
                "parents": {
                    "AudioToolbox.framework": [
                        {
                            "xml": "false",
                            "count": 1
                        }
                    ],
                    "SystemConfiguration.framework": [
                        {
                            "xml": "false",
                            "count": 1
                        }
                    ],
                    "MobileCoreServices.framework": [
                        {
                            "xml": "false",
                            "count": 1
                        }
                    ]
                }
            },
            "config.xml": {
                "parents": {
                    "/*": [
                        {
                            "xml": "<feature name=\"NiftyPushNotification\"><param name=\"ios-package\" value=\"NiftyPushNotification\" /></feature>",
                            "count": 1
                        }
                    ]
                }
            }
        }
    },
    "installed_plugins": {
        "plugin.push.nifty": {
            "PACKAGE_NAME": "com.nifty.cloud.mb.JsPush"
        }
    },
    "dependent_plugins": {}
}